{
  "2301-00697": {
    "title": "Complete analysis on QED corrections to Bq → τ+τ−",
    "authors": [
      "Yong-Kang Huang",
      "Yue Shen",
      "Xue-Chen Zhao",
      "Si-Hong Zhou"
    ],
    "submission_date": "2023-01-01",
    "revised_dates": [],
    "publication_venue": {
      "id": "cb5c6d2c-8c82-406e-b42e-b691561f3e4e",
      "name": "Journal of High Energy Physics",
      "type": "journal",
      "alternate_names": [
        "J High Energy Phys"
      ],
      "issn": "1029-8479",
      "url": "http://www.springer.com/13130",
      "alternate_urls": [
        "https://link.springer.com/journal/13130",
        "https://www.springer.com/physics/particle+and+nuclear+physics/journal/13130",
        "http://www.springer.com/physics/elementary/journal/13130"
      ]
    },
    "year": 2023
  },
  "2212-14430": {
    "title": "Structure-dependent QED effects in exclusive \nB\n decays at subleading power",
    "authors": [
      "C. Cornella",
      "Matthias König",
      "M. Neubert"
    ],
    "submission_date": "2022-01-01",
    "revised_dates": [],
    "publication_venue": null,
    "year": 2022
  },
  "2206-07501": {
    "title": "Averages of $b$-hadron, $c$-hadron, and $\\tau$-lepton properties as of 2021",
    "authors": [
      "H. C. Y. Amhis",
      "S. Banerjee",
      "E. Ben-Haim",
      "E. Bertholet",
      "F. Bernlochner",
      "M. Bona",
      "A. Bozek",
      "C. Bozzi",
      "J. Brodzicka",
      "V. Chobanova",
      "M. Chrzaszcz",
      "S. Duell",
      "U. Egede",
      "M. Gersabeck",
      "T. Gershon",
      "P. Goldenzweig",
      "K. Hayasaka",
      "D. Johnson",
      "M. Kenzie",
      "T. Kuhr",
      "O. Leroy",
      "A. Lusiani",
      "H.-L. Ma",
      "M. Margoni",
      "K. Miyabayashi",
      "R. Mizuk",
      "P. Naik",
      "T. N. Petric",
      "A. Oyanguren",
      "M. Prim",
      "A. Pompili",
      "M. Roney",
      "M. Rotondo",
      "O. Schneider",
      "C. Schwanda",
      "A. Schwartz",
      "J. Serrano",
      "A. Soffer",
      "D. Tonelli",
      "P. Urquijo",
      "J. Yelton"
    ],
    "submission_date": "2022-01-01",
    "revised_dates": [],
    "publication_venue": null,
    "year": 2022
  },
  "2205-10274": {
    "title": "First extraction of inclusive Vcb from q2 moments",
    "authors": [
      "F. Bernlochner",
      "M. Fael",
      "Kevin Olschewsky",
      "E. Persson",
      "R. van Tonder",
      "K. Vos",
      "M. Welsch"
    ],
    "submission_date": "2022-01-01",
    "revised_dates": [],
    "publication_venue": {
      "id": "cb5c6d2c-8c82-406e-b42e-b691561f3e4e",
      "name": "Journal of High Energy Physics",
      "type": "journal",
      "alternate_names": [
        "J High Energy Phys"
      ],
      "issn": "1029-8479",
      "url": "http://www.springer.com/13130",
      "alternate_urls": [
        "https://link.springer.com/journal/13130",
        "https://www.springer.com/physics/particle+and+nuclear+physics/journal/13130",
        "http://www.springer.com/physics/elementary/journal/13130"
      ]
    },
    "year": 2022
  },
  "2205-03427": {
    "title": "The forward-backward asymmetry and differences of partial moments in inclusive semileptonic $B$ decays",
    "authors": [
      "Florian Herren"
    ],
    "submission_date": "2022-01-01",
    "revised_dates": [],
    "publication_venue": {
      "id": "51571f5d-dd70-4af8-b981-935888dadd67",
      "name": "SciPost Physics",
      "alternate_names": [
        "Scipost Phys"
      ],
      "issn": "2542-4653",
      "url": "https://scipost.org/journals/scipost_physics/issues",
      "alternate_urls": [
        "https://scipost.org/SciPostPhys"
      ]
    },
    "year": 2022
  },
  "2205-03410": {
    "title": "A first glance to the kinematic moments of B → Xcℓν at third order",
    "authors": [
      "M. Fael",
      "K. Schönwald",
      "M. Steinhauser"
    ],
    "submission_date": "2022-01-01",
    "revised_dates": [],
    "publication_venue": {
      "id": "cb5c6d2c-8c82-406e-b42e-b691561f3e4e",
      "name": "Journal of High Energy Physics",
      "type": "journal",
      "alternate_names": [
        "J High Energy Phys"
      ],
      "issn": "1029-8479",
      "url": "http://www.springer.com/13130",
      "alternate_urls": [
        "https://link.springer.com/journal/13130",
        "https://www.springer.com/physics/particle+and+nuclear+physics/journal/13130",
        "http://www.springer.com/physics/elementary/journal/13130"
      ]
    },
    "year": 2022
  },
  "2204-09091": {
    "title": "Light-cone distribution amplitudes of heavy mesons with QED effects",
    "authors": [
      "M. Beneke",
      "Philipp Boer",
      "Jan-Niklas Toelstede",
      "K. Vos"
    ],
    "submission_date": "2022-01-01",
    "revised_dates": [],
    "publication_venue": {
      "id": "cb5c6d2c-8c82-406e-b42e-b691561f3e4e",
      "name": "Journal of High Energy Physics",
      "type": "journal",
      "alternate_names": [
        "J High Energy Phys"
      ],
      "issn": "1029-8479",
      "url": "http://www.springer.com/13130",
      "alternate_urls": [
        "https://link.springer.com/journal/13130",
        "https://www.springer.com/physics/particle+and+nuclear+physics/journal/13130",
        "http://www.springer.com/physics/elementary/journal/13130"
      ]
    },
    "year": 2022
  },
  "2112-00363": {
    "title": "$\\frac{|V_{ub}|}{|V_{cb}|}$ and Quest for New Physics",
    "authors": [
      "Anshika Bansal",
      "N. Mahajan",
      "Dayanand Mishra"
    ],
    "submission_date": "2021-01-01",
    "revised_dates": [],
    "publication_venue": null,
    "year": 2021
  },
  "2108-05589": {
    "title": "Light-cone distribution amplitudes of light mesons with QED effects",
    "authors": [
      "M. Beneke",
      "P. Böer",
      "Jan-Niklas Toelstede",
      "K. Vos"
    ],
    "submission_date": "2021-01-01",
    "revised_dates": [],
    "publication_venue": {
      "id": "cb5c6d2c-8c82-406e-b42e-b691561f3e4e",
      "name": "Journal of High Energy Physics",
      "type": "journal",
      "alternate_names": [
        "J High Energy Phys"
      ],
      "issn": "1029-8479",
      "url": "http://www.springer.com/13130",
      "alternate_urls": [
        "https://link.springer.com/journal/13130",
        "https://www.springer.com/physics/particle+and+nuclear+physics/journal/13130",
        "http://www.springer.com/physics/elementary/journal/13130"
      ]
    },
    "year": 2021
  },
  "2107-03819": {
    "title": "QED factorization of two-body non-leptonic and semi-leptonic B to charm decays",
    "authors": [
      "M. Beneke",
      "P. Böer",
      "Gael Finauri",
      "K. Vos"
    ],
    "submission_date": "2021-01-01",
    "revised_dates": [],
    "publication_venue": {
      "id": "cb5c6d2c-8c82-406e-b42e-b691561f3e4e",
      "name": "Journal of High Energy Physics",
      "type": "journal",
      "alternate_names": [
        "J High Energy Phys"
      ],
      "issn": "1029-8479",
      "url": "http://www.springer.com/13130",
      "alternate_urls": [
        "https://link.springer.com/journal/13130",
        "https://www.springer.com/physics/particle+and+nuclear+physics/journal/13130",
        "http://www.springer.com/physics/elementary/journal/13130"
      ]
    },
    "year": 2021
  },
  "2107-00604": {
    "title": "Three loop calculations and inclusive V",
    "authors": [
      "M. Bordone",
      "B. Capdevila",
      "P. Gambino"
    ],
    "submission_date": "2021-01-01",
    "revised_dates": [],
    "publication_venue": {
      "id": "a0b2cae8-7787-41eb-8cdd-30df6b48c1c4",
      "name": "Physics Letters B",
      "type": "journal",
      "alternate_names": [
        "Phys Lett B"
      ],
      "issn": "0370-2693",
      "url": "http://www.elsevier.com/wps/find/journaldescription.cws_home/505706/description#description",
      "alternate_urls": [
        "http://www.sciencedirect.com/science/journal/03702693",
        "https://www.journals.elsevier.com/physics-letters-b/"
      ]
    },
    "year": 2021
  },
  "2011-13654": {
    "title": "Third order corrections to the semileptonic \nb→c\n and the muon decays",
    "authors": [
      "M. Fael",
      "K. Schönwald",
      "M. Steinhauser"
    ],
    "submission_date": "2020-01-01",
    "revised_dates": [],
    "publication_venue": null,
    "year": 2020
  },
  "2008-10615": {
    "title": "QED factorization of non-leptonic B decays",
    "authors": [
      "M. Beneke",
      "P. Böer",
      "Jan-Niklas Toelstede",
      "K. Vos"
    ],
    "submission_date": "2020-01-01",
    "revised_dates": [],
    "publication_venue": {
      "id": "cb5c6d2c-8c82-406e-b42e-b691561f3e4e",
      "name": "Journal of High Energy Physics",
      "type": "journal",
      "alternate_names": [
        "J High Energy Phys"
      ],
      "issn": "1029-8479",
      "url": "http://www.springer.com/13130",
      "alternate_urls": [
        "https://link.springer.com/journal/13130",
        "https://www.springer.com/physics/particle+and+nuclear+physics/journal/13130",
        "http://www.springer.com/physics/elementary/journal/13130"
      ]
    },
    "year": 2020
  },
  "1911-01493": {
    "title": "On the effective theory of neutrino-electron and neutrino-quark interactions",
    "authors": [
      "R. Hill",
      "O. Tomalak"
    ],
    "submission_date": "2019-01-01",
    "revised_dates": [],
    "publication_venue": {
      "id": "a0b2cae8-7787-41eb-8cdd-30df6b48c1c4",
      "name": "Physics Letters B",
      "type": "journal",
      "alternate_names": [
        "Phys Lett B"
      ],
      "issn": "0370-2693",
      "url": "http://www.elsevier.com/wps/find/journaldescription.cws_home/505706/description#description",
      "alternate_urls": [
        "http://www.sciencedirect.com/science/journal/03702693",
        "https://www.journals.elsevier.com/physics-letters-b/"
      ]
    },
    "year": 2019
  },
  "1908-07011": {
    "title": "Power-enhanced leading-logarithmic QED corrections to Bq→ μ+μ−",
    "authors": [
      "M. Beneke",
      "C. Bobeth",
      "R. Szafron"
    ],
    "submission_date": "2019-01-01",
    "revised_dates": [],
    "publication_venue": {
      "id": "cb5c6d2c-8c82-406e-b42e-b691561f3e4e",
      "name": "Journal of High Energy Physics",
      "type": "journal",
      "alternate_names": [
        "J High Energy Phys"
      ],
      "issn": "1029-8479",
      "url": "http://www.springer.com/13130",
      "alternate_urls": [
        "https://link.springer.com/journal/13130",
        "https://www.springer.com/physics/particle+and+nuclear+physics/journal/13130",
        "http://www.springer.com/physics/elementary/journal/13130"
      ]
    },
    "year": 2019
  },
  "1905-02702": {
    "title": "Impacts of radiative corrections on measurements of lepton flavour universality in $${B} \\rightarrow {D} \\ell {{\\nu } _\\ell } $$ decays",
    "authors": [
      "S. Calí",
      "Suzanne Klaver",
      "M. Rotondo",
      "B. Sciascia"
    ],
    "submission_date": "2019-01-01",
    "revised_dates": [],
    "publication_venue": null,
    "year": 2019
  },
  "1605-07633": {
    "title": "On the standard model predictions for $$R_K$$RK and $$R_{K^*}$$RK∗",
    "authors": [
      "M. Bordone",
      "G. Isidori",
      "Andrea Pattori"
    ],
    "submission_date": "2016-01-01",
    "revised_dates": [],
    "publication_venue": null,
    "year": 2016
  },
  "1602-02678": {
    "title": "Additional information on heavy quark parameters from charged lepton forward-backward asymmetry",
    "authors": [
      "S. Turczyk"
    ],
    "submission_date": "2016-01-01",
    "revised_dates": [],
    "publication_venue": null,
    "year": 2016
  },
  "1503-04849": {
    "title": "Inclusive B -> X_s l^+ l^-: Complete angular analysis and a thorough study of collinear photons",
    "authors": [
      "T. Huber",
      "T. Hurth",
      "E. Lunghi"
    ],
    "submission_date": "2015-01-01",
    "revised_dates": [],
    "publication_venue": null,
    "year": 2015
  },
  "1311-0903": {
    "title": "B(s,d)→ℓ(+)ℓ(-) in the standard model with reduced theoretical uncertainty.",
    "authors": [
      "C. Bobeth",
      "M. Gorbahn",
      "Thomas Hermann",
      "M. Misiak",
      "Emmanuel Stamou",
      "M. Steinhauser"
    ],
    "submission_date": "2013-01-01",
    "revised_dates": [],
    "publication_venue": {
      "id": "16c9f9d4-bee1-435d-8c85-22a3deba109d",
      "name": "Physical Review Letters",
      "type": "journal",
      "alternate_names": [
        "Phys Rev Lett"
      ],
      "issn": "0031-9007",
      "url": "https://journals.aps.org/prl/",
      "alternate_urls": [
        "http://journals.aps.org/prl/",
        "http://prl.aps.org/"
      ]
    },
    "year": 2013
  },
  "1211-0960": {
    "title": "MuLan Measurement of the Positive Muon Lifetime and Determination of the Fermi Constant",
    "authors": [
      "V. Tishchenko",
      "S. Battu",
      "R. Carey",
      "D. B. Chitwood",
      "J. Crnkovic",
      "P. Debevec",
      "S. Dhamija",
      "W. Earle",
      "A. Gafarov",
      "K. Giovanetti",
      "T. Gorringe",
      "F. Gray",
      "Z. Hartwig",
      "D. Hertzog",
      "D. Hertzog",
      "B. Johnson",
      "P. Kammel",
      "P. Kammel",
      "B. Kiburg",
      "S. Kizilgul",
      "J. Kunkle",
      "B. Lauss",
      "I. Logashenko",
      "K. Lynch",
      "K. Lynch",
      "R. Mcnabb",
      "J. Miller",
      "F. Mulhauser",
      "F. Mulhauser",
      "C. Onderwater",
      "Q. Peng",
      "J. Phillips",
      "S. Rath",
      "B. Roberts",
      "D. Webber",
      "P. Winter",
      "B. Wolfe"
    ],
    "submission_date": "2012-01-01",
    "revised_dates": [],
    "publication_venue": null,
    "year": 2012
  },
  "1210-7939": {
    "title": "Phase space analysis for three and four massive particles in final states",
    "authors": [
      "H. Asatrian",
      "A. Hovhannisyan",
      "A. Yeghiazaryan"
    ],
    "submission_date": "2012-01-01",
    "revised_dates": [],
    "publication_venue": null,
    "year": 2012
  },
  "1107-3100": {
    "title": "B semileptonic moments at NNLO",
    "authors": [
      "P. Gambino"
    ],
    "submission_date": "2011-01-01",
    "revised_dates": [],
    "publication_venue": null,
    "year": 2011
  },
  "1010-5997": {
    "title": "Comparing different ansatzes to describe electroweak radiative corrections to exclusive semileptonic B meson decays into (pseudo)scalar final state mesons using Monte-Carlo techniques",
    "authors": [
      "F. Bernlochner",
      "M. Schonherr"
    ],
    "submission_date": "2010-01-01",
    "revised_dates": [],
    "publication_venue": null,
    "year": 2010
  },
  "1010-0991": {
    "title": "Measurement of the positive muon lifetime and determination of the Fermi constant to part-per-million precision.",
    "authors": [
      "D. Webber",
      "V. Tishchenko",
      "Q. Peng",
      "S. Battu",
      "R. Carey",
      "D. B. Chitwood",
      "J. Crnkovic",
      "P. Debevec",
      "S. Dhamija",
      "W. Earle",
      "A. Gafarov",
      "K. Giovanetti",
      "T. Gorringe",
      "F. Gray",
      "Z. Hartwig",
      "D. Hertzog",
      "B. Johnson",
      "P. Kammel",
      "B. Kiburg",
      "S. Kizilgul",
      "J. Kunkle",
      "B. Lauss",
      "I. Logashenko",
      "K. Lynch",
      "R. Mcnabb",
      "J. Miller",
      "F. Mulhauser",
      "C. Onderwater",
      "J. Phillips",
      "S. Rath",
      "B. Roberts",
      "P. Winter",
      "B. Wolfe"
    ],
    "submission_date": "2010-01-01",
    "revised_dates": [],
    "publication_venue": {
      "id": "16c9f9d4-bee1-435d-8c85-22a3deba109d",
      "name": "Physical Review Letters",
      "type": "journal",
      "alternate_names": [
        "Phys Rev Lett"
      ],
      "issn": "0031-9007",
      "url": "https://journals.aps.org/prl/",
      "alternate_urls": [
        "http://journals.aps.org/prl/",
        "http://prl.aps.org/"
      ]
    },
    "year": 2010
  },
  "1007-1887": {
    "title": "Radiative corrections in K→πℓ+ℓ− decays",
    "authors": [
      "B. Kubis",
      "R. Schmidt"
    ],
    "submission_date": "2010-01-01",
    "revised_dates": [],
    "publication_venue": null,
    "year": 2010
  },
  "0805-4119": {
    "title": "Electroweak Corrections to the Charm Quark Contribution to K+ ---> pi+ nu anti-nu",
    "authors": [
      "J. Brod",
      "M. Gorbahn"
    ],
    "submission_date": "2008-01-01",
    "revised_dates": [],
    "publication_venue": null,
    "year": 2008
  },
  "0803-0960": {
    "title": "Mass effects in muon and semileptonic b-->c decays.",
    "authors": [
      "A. Pak",
      "A. Czarnecki"
    ],
    "submission_date": "2008-01-01",
    "revised_dates": [],
    "publication_venue": {
      "id": "16c9f9d4-bee1-435d-8c85-22a3deba109d",
      "name": "Physical Review Letters",
      "type": "journal",
      "alternate_names": [
        "Phys Rev Lett"
      ],
      "issn": "0031-9007",
      "url": "https://journals.aps.org/prl/",
      "alternate_urls": [
        "http://journals.aps.org/prl/",
        "http://prl.aps.org/"
      ]
    },
    "year": 2008
  },
  "0712-3009": {
    "title": "Logarithmically enhanced corrections to the decay rate and forward–backward asymmetry in B¯→Xsℓ+ℓ−",
    "authors": [
      "T. Huber",
      "T. Hurth",
      "E. Lunghi"
    ],
    "submission_date": "2007-01-01",
    "revised_dates": [],
    "publication_venue": null,
    "year": 2007
  },
  "0709-2439": {
    "title": "Soft-photon corrections in multi-body meson decays",
    "authors": [
      "G. Isidori"
    ],
    "submission_date": "2007-01-01",
    "revised_dates": [],
    "publication_venue": null,
    "year": 2007
  }
}