{
  "2306-12646": {
    "title": "Learnability and Algorithm for Continual Learning",
    "authors": [
      "Gyuhak Kim",
      "Changnan Xiao",
      "Tatsuya Konishi",
      "Bin Liu"
    ],
    "submission_date": "2023-01-01",
    "revised_dates": [],
    "publication_venue": {
      "id": "fc0a208c-acb7-47dc-a0d4-af8190e21d29",
      "name": "International Conference on Machine Learning",
      "type": "conference",
      "alternate_names": [
        "ICML",
        "Int Conf Mach Learn"
      ],
      "url": "https://icml.cc/"
    },
    "year": 2023
  },
  "2306-03092": {
    "title": "Neuralangelo: High-Fidelity Neural Surface Reconstruction",
    "authors": [
      "Zhaoshuo Li",
      "T. Muller",
      "Alex Evans",
      "Russell H. Taylor",
      "M. Unberath",
      "Ming-Yu Liu",
      "Chen-Hsuan Lin"
    ],
    "submission_date": "2023-01-01",
    "revised_dates": [],
    "publication_venue": {
      "id": "768b87bb-8a18-4d9c-a161-4d483c776bcf",
      "name": "Computer Vision and Pattern Recognition",
      "type": "conference",
      "alternate_names": [
        "CVPR",
        "Comput Vis Pattern Recognit"
      ],
      "issn": "1063-6919",
      "url": "https://ieeexplore.ieee.org/xpl/conhome.jsp?punumber=1000147",
      "alternate_urls": [
        "https://en.wikipedia.org/wiki/Conference_on_Computer_Vision_and_Pattern_Recognition"
      ]
    },
    "year": 2023
  },
  "2304-02643": {
    "title": "Segment Anything",
    "authors": [
      "A. Kirillov",
      "Eric Mintun",
      "Nikhila Ravi",
      "Hanzi Mao",
      "Chloé Rolland",
      "Laura Gustafson",
      "Tete Xiao",
      "Spencer Whitehead",
      "A. Berg",
      "Wan-Yen Lo",
      "Piotr Dollár",
      "Ross B. Girshick"
    ],
    "submission_date": "2023-01-01",
    "revised_dates": [],
    "publication_venue": {
      "id": "7654260e-79f9-45c5-9663-d72027cf88f3",
      "name": "IEEE International Conference on Computer Vision",
      "type": "conference",
      "alternate_names": [
        "ICCV",
        "IEEE Int Conf Comput Vis",
        "ICCV Workshops",
        "ICCV Work"
      ],
      "url": "https://ieeexplore.ieee.org/xpl/conhome/1000149/all-proceedings"
    },
    "year": 2023
  },
  "2303-15149": {
    "title": "What Can Human Sketches Do for Object Detection?",
    "authors": [
      "Pinaki Nath Chowdhury",
      "A. Bhunia",
      "Aneeshan Sain",
      "Subhadeep Koley",
      "Tao Xiang",
      "Yi-Zhe Song"
    ],
    "submission_date": "2023-01-01",
    "revised_dates": [],
    "publication_venue": {
      "id": "768b87bb-8a18-4d9c-a161-4d483c776bcf",
      "name": "Computer Vision and Pattern Recognition",
      "type": "conference",
      "alternate_names": [
        "CVPR",
        "Comput Vis Pattern Recognit"
      ],
      "issn": "1063-6919",
      "url": "https://ieeexplore.ieee.org/xpl/conhome.jsp?punumber=1000147",
      "alternate_urls": [
        "https://en.wikipedia.org/wiki/Conference_on_Computer_Vision_and_Pattern_Recognition"
      ]
    },
    "year": 2023
  },
  "2212-02863": {
    "title": "Evidential Deep Learning for Class-Incremental Semantic Segmentation",
    "authors": [
      "Karl Holmquist",
      "Lena Klas'en",
      "M. Felsberg"
    ],
    "submission_date": "2022-01-01",
    "revised_dates": [],
    "publication_venue": {
      "id": "34a8e4b6-33c0-41d2-a418-fb738851fb68",
      "name": "Scandinavian Conference on Image Analysis",
      "type": "conference",
      "alternate_names": [
        "SCIA",
        "Scand Conf Image Anal"
      ]
    },
    "year": 2022
  },
  "2211-02633": {
    "title": "A Theoretical Study on Solving Continual Learning",
    "authors": [
      "Gyuhak Kim",
      "Changnan Xiao",
      "Tatsuya Konishi",
      "Zixuan Ke",
      "Bin Liu"
    ],
    "submission_date": "2022-01-01",
    "revised_dates": [],
    "publication_venue": {
      "id": "d9720b90-d60b-48bc-9df8-87a30b9a60dd",
      "name": "Neural Information Processing Systems",
      "type": "conference",
      "alternate_names": [
        "Neural Inf Process Syst",
        "NeurIPS",
        "NIPS"
      ],
      "url": "http://neurips.cc/"
    },
    "year": 2022
  },
  "2210-07242": {
    "title": "OpenOOD: Benchmarking Generalized Out-of-Distribution Detection",
    "authors": [
      "Jingkang Yang",
      "Pengyun Wang",
      "Dejian Zou",
      "Zitang Zhou",
      "Kun Ding",
      "Wen-Hsiao Peng",
      "Haoqi Wang",
      "Guangyao Chen",
      "Bo Li",
      "Yiyou Sun",
      "Xuefeng Du",
      "Kaiyang Zhou",
      "Wayne Zhang",
      "Dan Hendrycks",
      "Yixuan Li",
      "Ziwei Liu"
    ],
    "submission_date": "2022-01-01",
    "revised_dates": [],
    "publication_venue": {
      "id": "d9720b90-d60b-48bc-9df8-87a30b9a60dd",
      "name": "Neural Information Processing Systems",
      "type": "conference",
      "alternate_names": [
        "Neural Inf Process Syst",
        "NeurIPS",
        "NIPS"
      ],
      "url": "http://neurips.cc/"
    },
    "year": 2022
  },
  "2208-09734": {
    "title": "A Multi-Head Model for Continual Learning via Out-of-Distribution Replay",
    "authors": [
      "Gyuhak Kim",
      "Zixuan Ke",
      "Bin Liu"
    ],
    "submission_date": "2022-01-01",
    "revised_dates": [],
    "publication_venue": null,
    "year": 2022
  },
  "2207-03061": {
    "title": "Back to the Basics: Revisiting Out-of-Distribution Detection Baselines",
    "authors": [
      "Jo-Lan Kuan",
      "Jonas W. Mueller"
    ],
    "submission_date": "2022-01-01",
    "revised_dates": [],
    "publication_venue": {
      "id": "1901e811-ee72-4b20-8f7e-de08cd395a10",
      "name": "arXiv.org",
      "alternate_names": [
        "ArXiv"
      ],
      "issn": "2331-8422",
      "url": "https://arxiv.org"
    },
    "year": 2022
  },
  "2204-05462": {
    "title": "Out-Of-Distribution Detection In Unsupervised Continual Learning",
    "authors": [
      "Jiangpeng He",
      "F. Zhu"
    ],
    "submission_date": "2022-01-01",
    "revised_dates": [],
    "publication_venue": null,
    "year": 2022
  },
  "2203-09450": {
    "title": "Continual Learning Based on OOD Detection and Task Masking",
    "authors": [
      "Gyuhak Kim",
      "Sepideh Esmaeilpour",
      "Changnan Xiao",
      "Bing Liu"
    ],
    "submission_date": "2022-01-01",
    "revised_dates": [],
    "publication_venue": null,
    "year": 2022
  },
  "2112-10752": {
    "title": "High-Resolution Image Synthesis with Latent Diffusion Models",
    "authors": [
      "Robin Rombach",
      "A. Blattmann",
      "Dominik Lorenz",
      "Patrick Esser",
      "B. Ommer"
    ],
    "submission_date": "2021-01-01",
    "revised_dates": [],
    "publication_venue": {
      "id": "768b87bb-8a18-4d9c-a161-4d483c776bcf",
      "name": "Computer Vision and Pattern Recognition",
      "type": "conference",
      "alternate_names": [
        "CVPR",
        "Comput Vis Pattern Recognit"
      ],
      "issn": "1063-6919",
      "url": "https://ieeexplore.ieee.org/xpl/conhome.jsp?punumber=1000147",
      "alternate_urls": [
        "https://en.wikipedia.org/wiki/Conference_on_Computer_Vision_and_Pattern_Recognition"
      ]
    },
    "year": 2021
  },
  "2110-11334": {
    "title": "Generalized Out-of-Distribution Detection: A Survey",
    "authors": [
      "Jingkang Yang",
      "Kaiyang Zhou",
      "Yixuan Li",
      "Ziwei Liu"
    ],
    "submission_date": "2021-01-01",
    "revised_dates": [],
    "publication_venue": {
      "id": "939ee07c-6009-43f8-b884-69238b40659e",
      "name": "International Journal of Computer Vision",
      "type": "journal",
      "alternate_names": [
        "Int J Comput Vis"
      ],
      "issn": "0920-5691",
      "url": "https://www.springer.com/computer/image+processing/journal/11263",
      "alternate_urls": [
        "https://link.springer.com/journal/11263",
        "http://link.springer.com/journal/11263"
      ]
    },
    "year": 2021
  },
  "2107-10161": {
    "title": "Evidential Deep Learning for Open Set Action Recognition",
    "authors": [
      "Wentao Bao",
      "Qi Yu",
      "Yu Kong"
    ],
    "submission_date": "2021-01-01",
    "revised_dates": [],
    "publication_venue": {
      "id": "7654260e-79f9-45c5-9663-d72027cf88f3",
      "name": "IEEE International Conference on Computer Vision",
      "type": "conference",
      "alternate_names": [
        "ICCV",
        "IEEE Int Conf Comput Vis",
        "ICCV Workshops",
        "ICCV Work"
      ],
      "url": "https://ieeexplore.ieee.org/xpl/conhome/1000149/all-proceedings"
    },
    "year": 2021
  },
  "2107-03342": {
    "title": "A survey of uncertainty in deep neural networks",
    "authors": [
      "J. Gawlikowski",
      "Cedrique Rovile Njieutcheu Tassi",
      "Mohsin Ali",
      "Jongseo Lee",
      "Matthias Humt",
      "Jianxiang Feng",
      "Anna M. Kruspe",
      "Rudolph Triebel",
      "P. Jung",
      "R. Roscher",
      "M. Shahzad",
      "Wen Yang",
      "R. Bamler",
      "Xiaoxiang Zhu"
    ],
    "submission_date": "2021-01-01",
    "revised_dates": [],
    "publication_venue": {
      "id": "ea8553fe-2467-4367-afee-c4deb3754820",
      "name": "Artificial Intelligence Review",
      "type": "journal",
      "alternate_names": [
        "Artif Intell Rev"
      ],
      "issn": "0269-2821",
      "url": "https://link.springer.com/journal/10462"
    },
    "year": 2021
  },
  "2106-12964": {
    "title": "Continual Novelty Detection",
    "authors": [
      "Rahaf Aljundi",
      "Daniel Olmeda Reino",
      "N. Chumerin",
      "Richard E. Turner"
    ],
    "submission_date": "2021-01-01",
    "revised_dates": [],
    "publication_venue": null,
    "year": 2021
  },
  "2101-10423": {
    "title": "Online Continual Learning in Image Classification: An Empirical Survey",
    "authors": [
      "Zheda Mai",
      "Ruiwen Li",
      "Jihwan Jeong",
      "David Quispe",
      "Hyunwoo J. Kim",
      "S. Sanner"
    ],
    "submission_date": "2021-01-01",
    "revised_dates": [],
    "publication_venue": {
      "id": "df12d289-f447-47d3-8846-75e39de3ab57",
      "name": "Neurocomputing",
      "type": "journal",
      "issn": "0925-2312",
      "url": "http://www.elsevier.com/locate/neucom",
      "alternate_urls": [
        "http://www.sciencedirect.com/science/journal/09252312"
      ]
    },
    "year": 2021
  },
  "2012-13676": {
    "title": "Multidimensional Uncertainty-Aware Evidential Neural Networks",
    "authors": [
      "Yibo Hu",
      "Yuzhe Ou",
      "Xujiang Zhao",
      "Jin-Hee Cho",
      "Feng Chen"
    ],
    "submission_date": "2020-01-01",
    "revised_dates": [],
    "publication_venue": {
      "id": "bdc2e585-4e48-4e36-8af1-6d859763d405",
      "name": "AAAI Conference on Artificial Intelligence",
      "type": "conference",
      "alternate_names": [
        "National Conference on Artificial Intelligence",
        "National Conf Artif Intell",
        "AAAI Conf Artif Intell",
        "AAAI"
      ],
      "url": "http://www.aaai.org/"
    },
    "year": 2020
  },
  "2011-12328": {
    "title": "Generalized Variational Continual Learning",
    "authors": [
      "Noel Loo",
      "S. Swaroop",
      "Richard E. Turner"
    ],
    "submission_date": "2020-01-01",
    "revised_dates": [],
    "publication_venue": {
      "id": "939c6e1d-0d17-4d6e-8a82-66d960df0e40",
      "name": "International Conference on Learning Representations",
      "type": "conference",
      "alternate_names": [
        "Int Conf Learn Represent",
        "ICLR"
      ],
      "url": "https://iclr.cc/"
    },
    "year": 2020
  },
  "2011-06225": {
    "title": "A Review of Uncertainty Quantification in Deep Learning: Techniques, Applications and Challenges",
    "authors": [
      "Moloud Abdar",
      "Farhad Pourpanah",
      "Sadiq Hussain",
      "Dana Rezazadegan",
      "Li Liu",
      "M. Ghavamzadeh",
      "P. Fieguth",
      "Xiaochun Cao",
      "A. Khosravi",
      "U. R. Acharya",
      "V. Makarenkov",
      "S. Nahavandi"
    ],
    "submission_date": "2020-01-01",
    "revised_dates": [],
    "publication_venue": {
      "id": "06afdd0b-0d85-413f-af8a-c3045c12c561",
      "name": "Information Fusion",
      "type": "journal",
      "alternate_names": [
        "Inf Fusion"
      ],
      "issn": "1566-2535",
      "url": "https://www.journals.elsevier.com/information-fusion",
      "alternate_urls": [
        "http://www.sciencedirect.com/science/journal/15662535"
      ]
    },
    "year": 2020
  },
  "2010-15277": {
    "title": "Class-Incremental Learning: Survey and Performance Evaluation on Image Classification",
    "authors": [
      "Marc Masana",
      "Xialei Liu",
      "Bartłomiej Twardowski",
      "Mikel Menta",
      "Andrew D. Bagdanov",
      "Joost van de Weijer"
    ],
    "submission_date": "2020-01-01",
    "revised_dates": [],
    "publication_venue": {
      "id": "25248f80-fe99-48e5-9b8e-9baef3b8e23b",
      "name": "IEEE Transactions on Pattern Analysis and Machine Intelligence",
      "type": "journal",
      "alternate_names": [
        "IEEE Trans Pattern Anal Mach Intell"
      ],
      "issn": "0162-8828",
      "url": "http://www.computer.org/tpami/",
      "alternate_urls": [
        "http://www.computer.org/portal/web/tpami",
        "http://ieeexplore.ieee.org/servlet/opac?punumber=34"
      ]
    },
    "year": 2020
  },
  "2010-03759": {
    "title": "Energy-based Out-of-distribution Detection",
    "authors": [
      "Weitang Liu",
      "Xiaoyun Wang",
      "John Douglas Owens",
      "Yixuan Li"
    ],
    "submission_date": "2020-01-01",
    "revised_dates": [],
    "publication_venue": {
      "id": "d9720b90-d60b-48bc-9df8-87a30b9a60dd",
      "name": "Neural Information Processing Systems",
      "type": "conference",
      "alternate_names": [
        "Neural Inf Process Syst",
        "NeurIPS",
        "NIPS"
      ],
      "url": "http://neurips.cc/"
    },
    "year": 2020
  },
  "2007-08792": {
    "title": "Uncertainty Quantification and Deep Ensembles",
    "authors": [
      "R. Rahaman",
      "Alexandre Hoang Thiery"
    ],
    "submission_date": "2020-01-01",
    "revised_dates": [],
    "publication_venue": {
      "id": "d9720b90-d60b-48bc-9df8-87a30b9a60dd",
      "name": "Neural Information Processing Systems",
      "type": "conference",
      "alternate_names": [
        "Neural Inf Process Syst",
        "NeurIPS",
        "NIPS"
      ],
      "url": "http://neurips.cc/"
    },
    "year": 2020
  },
  "2007-08176": {
    "title": "CSI: Novelty Detection via Contrastive Learning on Distributionally Shifted Instances",
    "authors": [
      "Jihoon Tack",
      "Sangwoo Mo",
      "Jongheon Jeong",
      "Jinwoo Shin"
    ],
    "submission_date": "2020-01-01",
    "revised_dates": [],
    "publication_venue": {
      "id": "d9720b90-d60b-48bc-9df8-87a30b9a60dd",
      "name": "Neural Information Processing Systems",
      "type": "conference",
      "alternate_names": [
        "Neural Inf Process Syst",
        "NeurIPS",
        "NIPS"
      ],
      "url": "http://neurips.cc/"
    },
    "year": 2020
  },
  "2002-11107": {
    "title": "Very simple statistical evidence that AlphaGo has exceeded human limits in playing GO game",
    "authors": [
      "O-Kyang Kwon"
    ],
    "submission_date": "2020-01-01",
    "revised_dates": [],
    "publication_venue": {
      "id": "1901e811-ee72-4b20-8f7e-de08cd395a10",
      "name": "arXiv.org",
      "alternate_names": [
        "ArXiv"
      ],
      "issn": "2331-8422",
      "url": "https://arxiv.org"
    },
    "year": 2020
  },
  "1911-07053": {
    "title": "Maintaining Discrimination and Fairness in Class Incremental Learning",
    "authors": [
      "Bowen Zhao",
      "Xi Xiao",
      "Guojun Gan",
      "Bin Zhang",
      "Shutao Xia"
    ],
    "submission_date": "2019-01-01",
    "revised_dates": [],
    "publication_venue": {
      "id": "768b87bb-8a18-4d9c-a161-4d483c776bcf",
      "name": "Computer Vision and Pattern Recognition",
      "type": "conference",
      "alternate_names": [
        "CVPR",
        "Comput Vis Pattern Recognit"
      ],
      "issn": "1063-6919",
      "url": "https://ieeexplore.ieee.org/xpl/conhome.jsp?punumber=1000147",
      "alternate_urls": [
        "https://en.wikipedia.org/wiki/Conference_on_Computer_Vision_and_Pattern_Recognition"
      ]
    },
    "year": 2019
  },
  "1910-06864": {
    "title": "Quantifying Classification Uncertainty using Regularized Evidential Neural Networks",
    "authors": [
      "Xujiang Zhao",
      "Yuzhe Ou",
      "Lance M. Kaplan",
      "Feng Chen",
      "Jin-Hee Cho"
    ],
    "submission_date": "2019-01-01",
    "revised_dates": [],
    "publication_venue": {
      "id": "1901e811-ee72-4b20-8f7e-de08cd395a10",
      "name": "arXiv.org",
      "alternate_names": [
        "ArXiv"
      ],
      "issn": "2331-8422",
      "url": "https://arxiv.org"
    },
    "year": 2019
  },
  "1909-13719": {
    "title": "Randaugment: Practical automated data augmentation with a reduced search space",
    "authors": [
      "E. D. Cubuk",
      "Barret Zoph",
      "Jonathon Shlens",
      "Quoc V. Le"
    ],
    "submission_date": "2019-01-01",
    "revised_dates": [],
    "publication_venue": null,
    "year": 2019
  },
  "1906-02425": {
    "title": "Uncertainty-guided Continual Learning with Bayesian Neural Networks",
    "authors": [
      "Sayna Ebrahimi",
      "Mohamed Elhoseiny",
      "Trevor Darrell",
      "Marcus Rohrbach"
    ],
    "submission_date": "2019-01-01",
    "revised_dates": [],
    "publication_venue": {
      "id": "939c6e1d-0d17-4d6e-8a82-66d960df0e40",
      "name": "International Conference on Learning Representations",
      "type": "conference",
      "alternate_names": [
        "Int Conf Learn Represent",
        "ICLR"
      ],
      "url": "https://iclr.cc/"
    },
    "year": 2019
  },
  "1902-02476": {
    "title": "A Simple Baseline for Bayesian Uncertainty in Deep Learning",
    "authors": [
      "Wesley J. Maddox",
      "T. Garipov",
      "Pavel Izmailov",
      "D. Vetrov",
      "A. Wilson"
    ],
    "submission_date": "2019-01-01",
    "revised_dates": [],
    "publication_venue": {
      "id": "d9720b90-d60b-48bc-9df8-87a30b9a60dd",
      "name": "Neural Information Processing Systems",
      "type": "conference",
      "alternate_names": [
        "Neural Inf Process Syst",
        "NeurIPS",
        "NIPS"
      ],
      "url": "http://neurips.cc/"
    },
    "year": 2019
  },
  "1809-02058": {
    "title": "Memory Replay GANs: learning to generate images from new categories without forgetting",
    "authors": [
      "Chenshen Wu",
      "Luis Herranz",
      "Xialei Liu",
      "Yaxing Wang",
      "Joost van de Weijer",
      "B. Raducanu"
    ],
    "submission_date": "2018-01-01",
    "revised_dates": [],
    "publication_venue": {
      "id": "d9720b90-d60b-48bc-9df8-87a30b9a60dd",
      "name": "Neural Information Processing Systems",
      "type": "conference",
      "alternate_names": [
        "Neural Inf Process Syst",
        "NeurIPS",
        "NIPS"
      ],
      "url": "http://neurips.cc/"
    },
    "year": 2018
  },
  "1807-07356": {
    "title": "Aleatoric uncertainty estimation with test-time augmentation for medical image segmentation with convolutional neural networks",
    "authors": [
      "Guotai Wang",
      "Wenqi Li",
      "M. Aertsen",
      "J. Deprest",
      "S. Ourselin",
      "Tom Kamiel Magda Vercauteren"
    ],
    "submission_date": "2018-01-01",
    "revised_dates": [],
    "publication_venue": {
      "id": "df12d289-f447-47d3-8846-75e39de3ab57",
      "name": "Neurocomputing",
      "type": "journal",
      "issn": "0925-2312",
      "url": "http://www.elsevier.com/locate/neucom",
      "alternate_urls": [
        "http://www.sciencedirect.com/science/journal/09252312"
      ]
    },
    "year": 2018
  },
  "1806-01768": {
    "title": "Evidential Deep Learning to Quantify Classification Uncertainty",
    "authors": [
      "M. Sensoy",
      "M. Kandemir",
      "Lance M. Kaplan"
    ],
    "submission_date": "2018-01-01",
    "revised_dates": [],
    "publication_venue": {
      "id": "d9720b90-d60b-48bc-9df8-87a30b9a60dd",
      "name": "Neural Information Processing Systems",
      "type": "conference",
      "alternate_names": [
        "Neural Inf Process Syst",
        "NeurIPS",
        "NIPS"
      ],
      "url": "http://neurips.cc/"
    },
    "year": 2018
  },
  "1802-10501": {
    "title": "Predictive Uncertainty Estimation via Prior Networks",
    "authors": [
      "A. Malinin",
      "M. Gales"
    ],
    "submission_date": "2018-01-01",
    "revised_dates": [],
    "publication_venue": {
      "id": "d9720b90-d60b-48bc-9df8-87a30b9a60dd",
      "name": "Neural Information Processing Systems",
      "type": "conference",
      "alternate_names": [
        "Neural Inf Process Syst",
        "NeurIPS",
        "NIPS"
      ],
      "url": "http://neurips.cc/"
    },
    "year": 2018
  },
  "1802-07569": {
    "title": "Continual Lifelong Learning with Neural Networks: A Review",
    "authors": [
      "G. I. Parisi",
      "Ronald Kemker",
      "Jose L. Part",
      "Christopher Kanan",
      "Stefan Wermter"
    ],
    "submission_date": "2018-01-01",
    "revised_dates": [],
    "publication_venue": {
      "id": "a13f3cb8-2492-4ccb-9329-73a5ddcaab9b",
      "name": "Neural Networks",
      "type": "journal",
      "alternate_names": [
        "Neural Netw"
      ],
      "issn": "0893-6080",
      "url": "http://www.elsevier.com/locate/neunet",
      "alternate_urls": [
        "http://www.elsevier.com/wps/find/journaldescription.cws_home/841/description",
        "http://www.sciencedirect.com/science/journal/08936080"
      ]
    },
    "year": 2018
  },
  "1802-02950": {
    "title": "Rotate your Networks: Better Weight Consolidation and Less Catastrophic Forgetting",
    "authors": [
      "Xialei Liu",
      "Marc Masana",
      "Luis Herranz",
      "Joost van de Weijer",
      "Antonio M. López",
      "Andrew D. Bagdanov"
    ],
    "submission_date": "2018-01-01",
    "revised_dates": [],
    "publication_venue": {
      "id": "48782cc2-a3b4-44f3-95a4-2c4cb0f7245b",
      "name": "International Conference on Pattern Recognition",
      "type": "conference",
      "alternate_names": [
        "Pattern Recognit (ICPR Proc Int Conf",
        "Int Conf Pattern Recognit",
        "ICPR",
        "International conference on pattern recognition",
        "Int conf pattern recognit",
        "Pattern Recognition (ICPR), Proceedings of the International Conference on"
      ],
      "issn": "1041-3278",
      "alternate_issns": [
        "1051-4651"
      ],
      "url": "https://ieeexplore.ieee.org/xpl/conhome/1000545/all-proceedings",
      "alternate_urls": [
        "http://ieeexplore.ieee.org/servlet/opac?punumber=4740202"
      ]
    },
    "year": 2018
  },
  "1801-01423": {
    "title": "Overcoming catastrophic forgetting with hard attention to the task",
    "authors": [
      "J. Serrà",
      "Dídac Surís",
      "M. Miron",
      "Alexandros Karatzoglou"
    ],
    "submission_date": "2018-01-01",
    "revised_dates": [],
    "publication_venue": {
      "id": "fc0a208c-acb7-47dc-a0d4-af8190e21d29",
      "name": "International Conference on Machine Learning",
      "type": "conference",
      "alternate_names": [
        "ICML",
        "Int Conf Mach Learn"
      ],
      "url": "https://icml.cc/"
    },
    "year": 2018
  },
  "1710-10628": {
    "title": "Variational Continual Learning",
    "authors": [
      "Cuong V Nguyen",
      "Yingzhen Li",
      "T. Bui",
      "Richard E. Turner"
    ],
    "submission_date": "2017-01-01",
    "revised_dates": [],
    "publication_venue": {
      "id": "939c6e1d-0d17-4d6e-8a82-66d960df0e40",
      "name": "International Conference on Learning Representations",
      "type": "conference",
      "alternate_names": [
        "Int Conf Learn Represent",
        "ICLR"
      ],
      "url": "https://iclr.cc/"
    },
    "year": 2017
  },
  "1706-02690": {
    "title": "Enhancing The Reliability of Out-of-distribution Image Detection in Neural Networks",
    "authors": [
      "Shiyu Liang",
      "Yixuan Li",
      "R. Srikant"
    ],
    "submission_date": "2017-01-01",
    "revised_dates": [],
    "publication_venue": {
      "id": "939c6e1d-0d17-4d6e-8a82-66d960df0e40",
      "name": "International Conference on Learning Representations",
      "type": "conference",
      "alternate_names": [
        "Int Conf Learn Represent",
        "ICLR"
      ],
      "url": "https://iclr.cc/"
    },
    "year": 2017
  },
  "1706-08840": {
    "title": "Gradient Episodic Memory for Continual Learning",
    "authors": [
      "David Lopez-Paz",
      "Marc'Aurelio Ranzato"
    ],
    "submission_date": "2017-01-01",
    "revised_dates": [],
    "publication_venue": {
      "id": "d9720b90-d60b-48bc-9df8-87a30b9a60dd",
      "name": "Neural Information Processing Systems",
      "type": "conference",
      "alternate_names": [
        "Neural Inf Process Syst",
        "NeurIPS",
        "NIPS"
      ],
      "url": "http://neurips.cc/"
    },
    "year": 2017
  },
  "1705-08690": {
    "title": "Continual Learning with Deep Generative Replay",
    "authors": [
      "Hanul Shin",
      "Jung Kwon Lee",
      "Jaehong Kim",
      "Jiwon Kim"
    ],
    "submission_date": "2017-01-01",
    "revised_dates": [],
    "publication_venue": {
      "id": "d9720b90-d60b-48bc-9df8-87a30b9a60dd",
      "name": "Neural Information Processing Systems",
      "type": "conference",
      "alternate_names": [
        "Neural Inf Process Syst",
        "NeurIPS",
        "NIPS"
      ],
      "url": "http://neurips.cc/"
    },
    "year": 2017
  },
  "1703-04977": {
    "title": "What Uncertainties Do We Need in Bayesian Deep Learning for Computer Vision?",
    "authors": [
      "Alex Kendall",
      "Y. Gal"
    ],
    "submission_date": "2017-01-01",
    "revised_dates": [],
    "publication_venue": {
      "id": "d9720b90-d60b-48bc-9df8-87a30b9a60dd",
      "name": "Neural Information Processing Systems",
      "type": "conference",
      "alternate_names": [
        "Neural Inf Process Syst",
        "NeurIPS",
        "NIPS"
      ],
      "url": "http://neurips.cc/"
    },
    "year": 2017
  },
  "1612-01474": {
    "title": "Simple and Scalable Predictive Uncertainty Estimation using Deep Ensembles",
    "authors": [
      "Balaji Lakshminarayanan",
      "A. Pritzel",
      "C. Blundell"
    ],
    "submission_date": "2016-01-01",
    "revised_dates": [],
    "publication_venue": {
      "id": "d9720b90-d60b-48bc-9df8-87a30b9a60dd",
      "name": "Neural Information Processing Systems",
      "type": "conference",
      "alternate_names": [
        "Neural Inf Process Syst",
        "NeurIPS",
        "NIPS"
      ],
      "url": "http://neurips.cc/"
    },
    "year": 2016
  },
  "1612-00796": {
    "title": "Overcoming catastrophic forgetting in neural networks",
    "authors": [
      "J. Kirkpatrick",
      "Razvan Pascanu",
      "Neil C. Rabinowitz",
      "J. Veness",
      "Guillaume Desjardins",
      "Andrei A. Rusu",
      "Kieran Milan",
      "John Quan",
      "Tiago Ramalho",
      "A. Grabska-Barwinska",
      "D. Hassabis",
      "C. Clopath",
      "D. Kumaran",
      "R. Hadsell"
    ],
    "submission_date": "2016-01-01",
    "revised_dates": [],
    "publication_venue": {
      "id": "bb95bf2e-8383-4748-bf9d-d6906d091085",
      "name": "Proceedings of the National Academy of Sciences of the United States of America",
      "type": "journal",
      "alternate_names": [
        "PNAS",
        "PNAS online",
        "Proceedings of the National Academy of Sciences of the United States of America.",
        "Proc National Acad Sci",
        "Proceedings of the National Academy of Sciences",
        "Proc National Acad Sci u s Am"
      ],
      "issn": "0027-8424",
      "alternate_issns": [
        "1091-6490"
      ],
      "url": "https://www.jstor.org/journal/procnatiacadscie",
      "alternate_urls": [
        "http://www.pnas.org/",
        "https://www.pnas.org/",
        "http://www.jstor.org/journals/00278424.html",
        "www.pnas.org/"
      ]
    },
    "year": 2016
  },
  "1611-07725": {
    "title": "iCaRL: Incremental Classifier and Representation Learning",
    "authors": [
      "Sylvestre-Alvise Rebuffi",
      "Alexander Kolesnikov",
      "G. Sperl",
      "Christoph H. Lampert"
    ],
    "submission_date": "2016-01-01",
    "revised_dates": [],
    "publication_venue": {
      "id": "768b87bb-8a18-4d9c-a161-4d483c776bcf",
      "name": "Computer Vision and Pattern Recognition",
      "type": "conference",
      "alternate_names": [
        "CVPR",
        "Comput Vis Pattern Recognit"
      ],
      "issn": "1063-6919",
      "url": "https://ieeexplore.ieee.org/xpl/conhome.jsp?punumber=1000147",
      "alternate_urls": [
        "https://en.wikipedia.org/wiki/Conference_on_Computer_Vision_and_Pattern_Recognition"
      ]
    },
    "year": 2016
  },
  "1610-02136": {
    "title": "A Baseline for Detecting Misclassified and Out-of-Distribution Examples in Neural Networks",
    "authors": [
      "Dan Hendrycks",
      "Kevin Gimpel"
    ],
    "submission_date": "2016-01-01",
    "revised_dates": [],
    "publication_venue": {
      "id": "939c6e1d-0d17-4d6e-8a82-66d960df0e40",
      "name": "International Conference on Learning Representations",
      "type": "conference",
      "alternate_names": [
        "Int Conf Learn Represent",
        "ICLR"
      ],
      "url": "https://iclr.cc/"
    },
    "year": 2016
  },
  "1606-09282": {
    "title": "Learning without Forgetting",
    "authors": [
      "Zhizhong Li",
      "Derek Hoiem"
    ],
    "submission_date": "2016-01-01",
    "revised_dates": [],
    "publication_venue": {
      "id": "25248f80-fe99-48e5-9b8e-9baef3b8e23b",
      "name": "IEEE Transactions on Pattern Analysis and Machine Intelligence",
      "type": "journal",
      "alternate_names": [
        "IEEE Trans Pattern Anal Mach Intell"
      ],
      "issn": "0162-8828",
      "url": "http://www.computer.org/tpami/",
      "alternate_urls": [
        "http://www.computer.org/portal/web/tpami",
        "http://ieeexplore.ieee.org/servlet/opac?punumber=34"
      ]
    },
    "year": 2016
  },
  "1512-03385": {
    "title": "Deep Residual Learning for Image Recognition",
    "authors": [
      "Kaiming He",
      "X. Zhang",
      "Shaoqing Ren",
      "Jian Sun"
    ],
    "submission_date": "2015-01-01",
    "revised_dates": [],
    "publication_venue": {
      "id": "768b87bb-8a18-4d9c-a161-4d483c776bcf",
      "name": "Computer Vision and Pattern Recognition",
      "type": "conference",
      "alternate_names": [
        "CVPR",
        "Comput Vis Pattern Recognit"
      ],
      "issn": "1063-6919",
      "url": "https://ieeexplore.ieee.org/xpl/conhome.jsp?punumber=1000147",
      "alternate_urls": [
        "https://en.wikipedia.org/wiki/Conference_on_Computer_Vision_and_Pattern_Recognition"
      ]
    },
    "year": 2015
  },
  "1503-02531": {
    "title": "Distilling the Knowledge in a Neural Network",
    "authors": [
      "Geoffrey E. Hinton",
      "O. Vinyals",
      "J. Dean"
    ],
    "submission_date": "2015-01-01",
    "revised_dates": [],
    "publication_venue": {
      "id": "1901e811-ee72-4b20-8f7e-de08cd395a10",
      "name": "arXiv.org",
      "alternate_names": [
        "ArXiv"
      ],
      "issn": "2331-8422",
      "url": "https://arxiv.org"
    },
    "year": 2015
  },
  "1412-1897": {
    "title": "Deep neural networks are easily fooled: High confidence predictions for unrecognizable images",
    "authors": [
      "Anh Totti Nguyen",
      "J. Yosinski",
      "J. Clune"
    ],
    "submission_date": "2014-01-01",
    "revised_dates": [],
    "publication_venue": {
      "id": "768b87bb-8a18-4d9c-a161-4d483c776bcf",
      "name": "Computer Vision and Pattern Recognition",
      "type": "conference",
      "alternate_names": [
        "CVPR",
        "Comput Vis Pattern Recognit"
      ],
      "issn": "1063-6919",
      "url": "https://ieeexplore.ieee.org/xpl/conhome.jsp?punumber=1000147",
      "alternate_urls": [
        "https://en.wikipedia.org/wiki/Conference_on_Computer_Vision_and_Pattern_Recognition"
      ]
    },
    "year": 2014
  }
}