{
  "2205-06520": {
    "title": "Simplex Closing Probabilities in Directed Graphs",
    "authors": [
      "F. Unger",
      "Jonathan Krebs",
      "Michael G. Müller"
    ],
    "submission_date": "2022-01-01",
    "revised_dates": [],
    "publication_venue": {
      "id": "d9046364-b534-4cb3-9e20-4dafd5fac877",
      "name": "Computational geometry",
      "type": "journal",
      "alternate_names": [
        "Comput geom",
        "Computational Geometry: Theory and Applications",
        "Comput Geom Theory Appl"
      ],
      "issn": "0925-7721",
      "url": "http://www.elsevier.com/wps/find/journaldescription.cws_home/505629/description#description",
      "alternate_urls": [
        "https://www.journals.elsevier.com/computational-geometry/",
        "http://www.sciencedirect.com/science/journal/09257721"
      ]
    },
    "year": 2022
  },
  "2202-07307": {
    "title": "Simplicial $q$-connectivity of directed graphs with applications to network analysis",
    "authors": [
      "Henri Riihimaki"
    ],
    "submission_date": "2022-01-01",
    "revised_dates": [],
    "publication_venue": null,
    "year": 2022
  },
  "2104-07737": {
    "title": "A random persistence diagram generator",
    "authors": [
      "T. Papamarkou",
      "Farzana Nasrin",
      "A. Lawson",
      "Na Gong",
      "Orlando Rios",
      "V. Maroulas"
    ],
    "submission_date": "2021-01-01",
    "revised_dates": [],
    "publication_venue": {
      "id": "dd522c0a-e715-4d95-9ed7-e60346254ddf",
      "name": "Statistics and computing",
      "type": "journal",
      "alternate_names": [
        "Stat comput",
        "Stat Comput",
        "Statistics and Computing"
      ],
      "issn": "0960-3174",
      "alternate_issns": [
        "1431-8784"
      ],
      "url": "https://link.springer.com/journal/11222",
      "alternate_urls": [
        "http://www.springerlink.com/content/100219/"
      ]
    },
    "year": 2021
  },
  "1906-10458": {
    "title": "Computing Persistent Homology of Directed Flag Complexes",
    "authors": [
      "Daniel Luetgehetmann",
      "Dejan Govc",
      "Jason P. Smith",
      "R. Levi"
    ],
    "submission_date": "2019-01-01",
    "revised_dates": [],
    "publication_venue": {
      "id": "e95c8d18-09be-464f-a3cf-5b2637f0eff6",
      "name": "Algorithms",
      "type": "journal",
      "issn": "1999-4893",
      "url": "http://www.e-helvetica.nb.admin.ch/directAccess?callnumber=bel-150910",
      "alternate_urls": [
        "http://nbn-resolving.de/urn/resolver.pl?urn=urn:nbn:ch:bel-150910",
        "http://www.mdpi.com/journal/algorithms",
        "http://www.mdpi.com/journal/algorithms/"
      ]
    },
    "year": 2019
  },
  "1705-10298": {
    "title": "Construction of and efficient sampling from the simplicial configuration model.",
    "authors": [
      "Jean-Gabriel Young",
      "G. Petri",
      "F. Vaccarino",
      "Alice Patania"
    ],
    "submission_date": "2017-01-01",
    "revised_dates": [],
    "publication_venue": {
      "id": "19842b7b-a4d1-4f9a-9714-87d878cf6e73",
      "name": "Physical Review E",
      "type": "journal",
      "alternate_names": [
        "Phys rev E",
        "Physical review. E",
        "Phys Rev E"
      ],
      "issn": "1539-3755",
      "alternate_issns": [
        "1550-2376",
        "2470-0045"
      ],
      "url": "https://journals.aps.org/pre/",
      "alternate_urls": [
        "http://pre.aps.org/",
        "http://journals.aps.org/pre/"
      ]
    },
    "year": 2017
  },
  "1608-00607": {
    "title": "Configuring Random Graph Models with Fixed Degree Sequences",
    "authors": [
      "B. Fosdick",
      "D. Larremore",
      "Joel Nishimura",
      "J. Ugander"
    ],
    "submission_date": "2016-01-01",
    "revised_dates": [],
    "publication_venue": {
      "id": "8f59dd66-e4cd-4341-8ea9-9a03d965a009",
      "name": "SIAM Review",
      "type": "journal",
      "alternate_names": [
        "SIAM Rev",
        "Siam Rev",
        "Siam Review"
      ],
      "issn": "0036-1445",
      "url": "https://www.jstor.org/journal/siamreview",
      "alternate_urls": [
        "http://www.jstor.org/journals/00361445.html",
        "https://epubs.siam.org/journal/siread",
        "http://www.siam.org/journals/sirev.php"
      ]
    },
    "year": 2016
  },
  "1601-01580": {
    "title": "Cliques of Neurons Bound into Cavities Provide a Missing Link between Structure and Function",
    "authors": [
      "Michael W. Reimann",
      "Max Nolte",
      "Martina Scolamiero",
      "Katharine Turner",
      "R. Perin",
      "G. Chindemi",
      "Paweł Dłotko",
      "R. Levi",
      "K. Hess",
      "H. Markram"
    ],
    "submission_date": "2016-01-01",
    "revised_dates": [],
    "publication_venue": {
      "id": "8c456f98-9892-42ac-9b16-418755f01550",
      "name": "Frontiers in Computational Neuroscience",
      "type": "journal",
      "alternate_names": [
        "Front Comput Neurosci"
      ],
      "issn": "1662-5188",
      "url": "http://www.frontiersin.org/computational_neuroscience",
      "alternate_urls": [
        "http://www.frontiersin.org/computationalneuroscience/",
        "https://www.frontiersin.org/journals/computational-neuroscience"
      ]
    },
    "year": 2016
  },
  "1502-06172": {
    "title": "Clique topology reveals intrinsic geometric structure in neural correlations",
    "authors": [
      "Chad Giusti",
      "E. Pastalkova",
      "C. Curto",
      "V. Itskov"
    ],
    "submission_date": "2015-01-01",
    "revised_dates": [],
    "publication_venue": {
      "id": "bb95bf2e-8383-4748-bf9d-d6906d091085",
      "name": "Proceedings of the National Academy of Sciences of the United States of America",
      "type": "journal",
      "alternate_names": [
        "PNAS",
        "PNAS online",
        "Proceedings of the National Academy of Sciences of the United States of America.",
        "Proc National Acad Sci",
        "Proceedings of the National Academy of Sciences",
        "Proc National Acad Sci u s Am"
      ],
      "issn": "0027-8424",
      "alternate_issns": [
        "1091-6490"
      ],
      "url": "https://www.jstor.org/journal/procnatiacadscie",
      "alternate_urls": [
        "http://www.pnas.org/",
        "https://www.pnas.org/",
        "http://www.jstor.org/journals/00278424.html",
        "www.pnas.org/"
      ]
    },
    "year": 2015
  },
  "0907-2373": {
    "title": "Structural Properties of the Caenorhabditis elegans Neuronal Network",
    "authors": [
      "L. Varshney",
      "Beth L. Chen",
      "Eric Paniagua",
      "D. Hall",
      "D. Chklovskii"
    ],
    "submission_date": "2009-01-01",
    "revised_dates": [],
    "publication_venue": null,
    "year": 2009
  }
}